behave_html_formatter/__init__.py
behave_html_formatter/behave.css
behave_html_formatter/behave.js
behave_html_formatter/behave.min.css
behave_html_formatter/behave.min.js
behave_html_formatter/html.py
behave_html_formatter-0.9.10.dist-info/LICENSE
behave_html_formatter-0.9.10.dist-info/METADATA
behave_html_formatter-0.9.10.dist-info/WHEEL
behave_html_formatter-0.9.10.dist-info/top_level.txt
behave_html_formatter-0.9.10.dist-info/RECORD
